sempyro/__init__.py
sempyro/rdf_model.py
sempyro/adms/__init__.py
sempyro/adms/identifier.py
sempyro/dcat/__init__.py
sempyro/dcat/data_service.py
sempyro/dcat/dataset_series.py
sempyro/dcat/dcat_attribution.py
sempyro/dcat/dcat_catalog.py
sempyro/dcat/dcat_catalog_record.py
sempyro/dcat/dcat_dataset.py
sempyro/dcat/dcat_distribution.py
sempyro/dcat/dcat_relationship.py
sempyro/dcat/dcat_resource.py
sempyro/dqv/__init__.py
sempyro/dqv/quality_certificate.py
sempyro/foaf/__init__.py
sempyro/foaf/agent.py
sempyro/foaf/project.py
sempyro/geo/__init__.py
sempyro/geo/spatial.py
sempyro/hri_dcat/__init__.py
sempyro/hri_dcat/hri_agent.py
sempyro/hri_dcat/hri_catalog.py
sempyro/hri_dcat/hri_data_service.py
sempyro/hri_dcat/hri_dataset.py
sempyro/hri_dcat/hri_dataset_series.py
sempyro/hri_dcat/hri_distribution.py
sempyro/hri_dcat/hri_vcard.py
sempyro/hri_dcat/vocabularies.py
sempyro/namespaces/ADMS.py
sempyro/namespaces/DCATAPv3.py
sempyro/namespaces/DCATv3.py
sempyro/namespaces/DISCO.py
sempyro/namespaces/DPV.py
sempyro/namespaces/DQV.py
sempyro/namespaces/FREQ.py
sempyro/namespaces/GEOSPARQL.py
sempyro/namespaces/GREG.py
sempyro/namespaces/HEALTHDCATAP.py
sempyro/namespaces/LOCN.py
sempyro/namespaces/OA.py
sempyro/namespaces/__init__.py
sempyro/odrl/__init__.py
sempyro/odrl/policy.py
sempyro/prov/__init__.py
sempyro/prov/prov_classes.py
sempyro/spdx/__init__.py
sempyro/spdx/spdx_classes.py
sempyro/time/__init__.py
sempyro/time/dcat_time_models.py
sempyro/utils/__init__.py
sempyro/utils/constants.py
sempyro/utils/validator_functions.py
sempyro/vcard/__init__.py
sempyro/vcard/vcard.py
sempyro-2.1.0.dist-info/METADATA
sempyro-2.1.0.dist-info/WHEEL
sempyro-2.1.0.dist-info/licenses/LICENSE
sempyro-2.1.0.dist-info/RECORD
