Metadata-Version: 2.4
Name: sempyro
Version: 2.1.0
Summary: SeMPyRO (for Semantic Models Python Pydantic RDF Ontology) is a Pydantic models representing classes of DCAT-AP v3 data model.
Project-URL: Documentation, https://github.com/Health-RI/SeMPyRO/tree/main/docs
Project-URL: Repository, https://github.com/Health-RI/SeMPyRO.git
Project-URL: Issues, https://github.com/Health-RI/SeMPyRO/issues
Author-email: Anastasia Nayden <anastasia.nayden@health-ri.nl>, Mark Janse <mark.janse@health-ri.nl>
License: Apache License
License-File: LICENSE
Keywords: DCAT,DCAT-AP,data model,pydantic,rdf
Classifier: Development Status :: 4 - Beta
Classifier: Programming Language :: Python
Classifier: Programming Language :: Python :: 3.8
Classifier: Programming Language :: Python :: 3.9
Classifier: Programming Language :: Python :: 3.10
Classifier: Programming Language :: Python :: 3.11
Classifier: Programming Language :: Python :: 3.12
Classifier: Programming Language :: Python :: Implementation :: CPython
Classifier: Programming Language :: Python :: Implementation :: PyPy
Requires-Python: >=3.8.1
Requires-Dist: email-validator==2.3.0
Requires-Dist: pydantic~=2.10.6
Requires-Dist: python-dateutil~=2.8
Requires-Dist: rdflib>=7.0.0
Requires-Dist: ruamel-yaml~=0.18.5
Provides-Extra: notebook-docs
Requires-Dist: fairclient>=1.0.0; extra == 'notebook-docs'
Requires-Dist: notebook>=7.0.6; extra == 'notebook-docs'
Requires-Dist: pandas>=1.5.3; extra == 'notebook-docs'
Requires-Dist: tabulate>=0.9.0; extra == 'notebook-docs'
